sentimentAnalysisPkg/__init__.py
sentimentAnalysisPkg/basicSentimentAnalysis.py
sentimentAnalysisPkg-0.0.4.dist-info/METADATA
sentimentAnalysisPkg-0.0.4.dist-info/WHEEL
sentimentAnalysisPkg-0.0.4.dist-info/top_level.txt
sentimentAnalysisPkg-0.0.4.dist-info/RECORD
