Metadata-Version: 2.1
Name: sentimentAnalysisPkg
Version: 0.0.4
Summary: package to perform sentiment analysis on financial social media posts
Home-page: https://github.com/p-hiroshige/sentimentAnalysis.git
Author: Example Author
Author-email: author@example.com
License: UNKNOWN
Platform: UNKNOWN
Classifier: Programming Language :: Python :: 3
Classifier: License :: OSI Approved :: MIT License
Classifier: Operating System :: OS Independent
